opsrampcli/DataSource.py
opsrampcli/JSONDataSource.py
opsrampcli/ServiceNowDataSource.py
opsrampcli/URLDataSource.py
opsrampcli/__init.py__
opsrampcli/alerts.py
opsrampcli/argparsing.py
opsrampcli/customattrs.py
opsrampcli/discovery.py
opsrampcli/escalationpolicies.py
opsrampcli/incidents.py
opsrampcli/integrations.py
opsrampcli/monitoring.py
opsrampcli/opsrampcli.py
opsrampcli/opsrampenv.py
opsrampcli/resources.py
opsrampcli/servicemaps.py
opsrampcli/test.py
opsrampcli-1.7.2.dist-info/METADATA
opsrampcli-1.7.2.dist-info/WHEEL
opsrampcli-1.7.2.dist-info/entry_points.txt
opsrampcli-1.7.2.dist-info/RECORD
