Metadata-Version: 2.3
Name: opsrampcli
Version: 1.7.2
Summary: A command line interface for OpsRamp
License: MIT
Author: Michael Friedhoff
Author-email: michael.friedhoff@opsramp.com
Requires-Python: >=3.12,<4.0.0
Classifier: License :: OSI Approved :: MIT License
Classifier: Programming Language :: Python :: 3
Classifier: Programming Language :: Python :: 3.12
Classifier: Programming Language :: Python :: 3.13
Requires-Dist: DateTime
Requires-Dist: PyYAML
Requires-Dist: XlsxWriter
Requires-Dist: aiohttp
Requires-Dist: json5
Requires-Dist: numpy
Requires-Dist: openpyxl
Requires-Dist: pandas
Requires-Dist: requests
Requires-Dist: requests-ntlm
